nestedarchive/__init__.py
nestedarchive/get.py
nestedarchive/remote.py
nestedarchive-0.3.1.dist-info/LICENSE.md
nestedarchive-0.3.1.dist-info/METADATA
nestedarchive-0.3.1.dist-info/WHEEL
nestedarchive-0.3.1.dist-info/top_level.txt
nestedarchive-0.3.1.dist-info/RECORD
