Metadata-Version: 2.1
Name: nestedarchive
Version: 0.3.1
Summary: Seamless reading of nested archives
Home-page: https://github.com/omertuc/nestedarchive
Author: Omer Tuchfeld
Author-email: omer@tuchfeld.dev
License: MIT
Classifier: License :: OSI Approved :: MIT License
Classifier: Programming Language :: Python :: 3
Classifier: Programming Language :: Python :: 3.7
License-File: LICENSE.md
Requires-Dist: requests
